{"data_mtime":1755886585,"dep_lines":[295,308,295,373,569,38,39,40,41,42,296,373,34,35,36,38,845,1,1,1,1,1,1,1,1,1,1,1,1,1,1,1,1,1,1,1,1,1,1,1,1,1],"dep_prios":[20,20,20,20,20,10,10,10,10,10,20,20,10,10,10,20,10,5,20,20,20,20,20,20,20,20,20,20,20,20,20,20,20,20,20,20,20,30,30,30,30,30],"dependencies":["pyasn1.codec.der.decoder","pyasn1.codec.der.encoder","pyasn1.codec.der","pyasn1.type.univ","pyasn1.type.namedtype","rsa.prime","rsa.pem","rsa.common","rsa.randnum","rsa.core","rsa.asn1","pyasn1.type","threading","typing","warnings","rsa","doctest","builtins","os","pprint","functools","traitlets.utils.warnings","inspect","operator","json","html","re","logging","traceback","string","dataclasses","sys","collections","copy","itertools","types","contextlib","_frozen_importlib","_thread","_typeshed","abc","typing_extensions"],"hash":"569c6830cfcd134830af2506bebf6823da34076b","id":"rsa.key","ignore_all":true,"interface_hash":"e26650bee7ab5bdb0709dda704bb73df344c8c09","mtime":1747684619,"options":{"allow_redefinition":false,"allow_untyped_globals":false,"always_false":[],"always_true":[],"bazel":false,"check_untyped_defs":true,"disable_bytearray_promotion":false,"disable_error_code":[],"disable_memoryview_promotion":false,"disabled_error_codes":[],"disallow_any_decorated":false,"disallow_any_explicit":false,"disallow_any_expr":false,"disallow_any_generics":false,"disallow_any_unimported":false,"disallow_incomplete_defs":true,"disallow_subclassing_any":false,"disallow_untyped_calls":false,"disallow_untyped_decorators":true,"disallow_untyped_defs":true,"enable_error_code":[],"enabled_error_codes":[],"extra_checks":false,"follow_imports":"normal","follow_imports_for_stubs":false,"follow_untyped_imports":false,"ignore_errors":false,"ignore_missing_imports":false,"implicit_optional":false,"implicit_reexport":true,"local_partial_types":false,"mypyc":false,"old_type_inference":false,"platform":"darwin","plugins":[],"strict_bytes":false,"strict_concatenate":false,"strict_equality":false,"strict_optional":true,"warn_no_return":true,"warn_return_any":true,"warn_unreachable":true,"warn_unused_ignores":true},"path":"/Library/Frameworks/Python.framework/Versions/3.12/lib/python3.12/site-packages/rsa/key.py","plugin_data":null,"size":27427,"suppressed":[],"version_id":"1.15.0"}